{
  "project_info": {
    "project_number": "11688771619",
    "project_id": "stayfit-3b827",
    "storage_bucket": "stayfit-3b827.firebasestorage.app"
  },
  "client": [
    {
      "client_info": {
        "mobilesdk_app_id": "1:11688771619:android:fa04526da8ca56f557b196",
        "android_client_info": {
          "package_name": "com.fitnesscompany.stayfit"
        }
      },
      "oauth_client": [],
      "api_key": [
        {
          "current_key": "AIzaSyBB-VI2sc0gSv3XrH5zVmhBb2ypTqKjbpY"
        }
      ],
      "services": {
        "appinvite_service": {
          "other_platform_oauth_client": []
        }
      }
    }
  ],
  "configuration_version": "1"
}